himalaya/__init__.py
himalaya/progress_bar.py
himalaya/scoring.py
himalaya/utils.py
himalaya/validation.py
himalaya/viz.py
himalaya/backend/__init__.py
himalaya/backend/_utils.py
himalaya/backend/cupy.py
himalaya/backend/numpy.py
himalaya/backend/torch.py
himalaya/backend/torch_cuda.py
himalaya/kernel_ridge/__init__.py
himalaya/kernel_ridge/_hyper_gradient.py
himalaya/kernel_ridge/_kernelizer.py
himalaya/kernel_ridge/_kernels.py
himalaya/kernel_ridge/_predictions.py
himalaya/kernel_ridge/_random_search.py
himalaya/kernel_ridge/_sklearn_api.py
himalaya/kernel_ridge/_solvers.py
himalaya/lasso/__init__.py
himalaya/lasso/_group_lasso.py
himalaya/lasso/_sklearn_api.py
himalaya/ridge/__init__.py
himalaya/ridge/_column.py
himalaya/ridge/_random_search.py
himalaya/ridge/_sklearn_api.py
himalaya/ridge/_solvers.py
himalaya-0.4.9.dist-info/LICENSE.md
himalaya-0.4.9.dist-info/METADATA
himalaya-0.4.9.dist-info/WHEEL
himalaya-0.4.9.dist-info/top_level.txt
himalaya-0.4.9.dist-info/RECORD
