Metadata-Version: 2.1
Name: himalaya
Version: 0.4.9
Summary: Multiple-target machine learning
Home-page: https://github.com/gallantlab/himalaya
Maintainer: Tom Dupre la Tour
Maintainer-email: tomdlt@berkeley.edu
License: BSD (3-clause)
License-File: LICENSE.md
Requires-Dist: numpy
Requires-Dist: scikit-learn
Provides-Extra: all
Requires-Dist: cupy ; extra == 'all'
Requires-Dist: matplotlib ; extra == 'all'
Requires-Dist: pytest ; extra == 'all'
Requires-Dist: pytest-rerunfailures ; extra == 'all'
Requires-Dist: torch ; extra == 'all'
Provides-Extra: all_backends
Requires-Dist: cupy ; extra == 'all_backends'
Requires-Dist: torch ; extra == 'all_backends'
Provides-Extra: doc
Requires-Dist: cupy ; extra == 'doc'
Requires-Dist: matplotlib ; extra == 'doc'
Requires-Dist: numpydoc ; extra == 'doc'
Requires-Dist: sphinx ; extra == 'doc'
Requires-Dist: sphinx-gallery ; extra == 'doc'
Requires-Dist: sphinxcontrib-mermaid ; extra == 'doc'
Requires-Dist: torch ; extra == 'doc'
Provides-Extra: github
Requires-Dist: matplotlib ; extra == 'github'
Requires-Dist: pytest ; extra == 'github'
Requires-Dist: pytest-rerunfailures ; extra == 'github'
Requires-Dist: torch ; extra == 'github'
Provides-Extra: test
Requires-Dist: cupy ; extra == 'test'
Requires-Dist: matplotlib ; extra == 'test'
Requires-Dist: pytest ; extra == 'test'
Requires-Dist: torch ; extra == 'test'
Provides-Extra: viz
Requires-Dist: matplotlib ; extra == 'viz'
